nlql/__init__.py
nlql/exceptions.py
nlql/nlql.py
nlql/executor/__init__.py
nlql/executor/executor.py
nlql/executor/operators.py
nlql/executor/semantic.py
nlql/executor/sentiment.py
nlql/lexer/__init__.py
nlql/lexer/lexer.py
nlql/lexer/token.py
nlql/optimization/__init__.py
nlql/optimization/cache.py
nlql/optimization/index.py
nlql/parser/__init__.py
nlql/parser/ast.py
nlql/parser/parser.py
nlql/utils/__init__.py
nlql/utils/text_unit.py
tests/__init__.py
tests/test_executor.py
tests/test_lexer.py
tests/test_nlql.py
tests/test_operators.py
tests/test_parser.py
tests/test_text_unit.py
nlql-0.1.3.dist-info/LICENSE
nlql-0.1.3.dist-info/METADATA
nlql-0.1.3.dist-info/WHEEL
nlql-0.1.3.dist-info/top_level.txt
nlql-0.1.3.dist-info/RECORD
