Metadata-Version: 2.1
Name: nlql
Version: 0.1.3
Summary: NLQL (Natural Language Query Language) is a tool that helps you search through text using simple commands that look like SQL. Just like how SQL helps you find information in databases, NLQL helps you find information in regular text.
Home-page: https://github.com/natural-language-query-language/nlql-python
Author: Okysu
Author-email: yby@ecanse.com
License: MIT Licence
Keywords: natural language,sql,llm,ai,rag,nlql,nlp
Requires-Python: >=3.9.0
License-File: LICENSE
Requires-Dist: numpy
